mkdocs_issues_plugin/__init__.py
mkdocs_issues_plugin/plugin.py
mkdocs_issues_plugin-0.1.2.dist-info/LICENSE
mkdocs_issues_plugin-0.1.2.dist-info/METADATA
mkdocs_issues_plugin-0.1.2.dist-info/WHEEL
mkdocs_issues_plugin-0.1.2.dist-info/entry_points.txt
mkdocs_issues_plugin-0.1.2.dist-info/top_level.txt
mkdocs_issues_plugin-0.1.2.dist-info/RECORD
